{"stats":{"minecraft:used":{"farmersdelight:iron_knife":35,"minecraft:stone_sword":48,"minecraft:stone_shovel":235,"minecraft:stone_pickaxe":70,"minecraft:oak_planks":85,"minecraft:chest":2,"minecraft:sandstone":1,"minecraft:torch":2,"minecraft:dirt":150,"minecraft:crafting_table":3,"minecraft:gray_concrete":56,"minecraft:dark_oak_planks":1,"minecraft:sea_lantern":7,"minecraft:grass_block":435,"minecraft:oak_stairs":8,"minecraft:diorite_wall":95,"minecraft:stone_axe":123,"farmersdelight:cooked_bacon":2,"farmersdelight:cutting_board":2,"minecraft:cobblestone":125,"minecraft:gray_bed":4,"minecraft:white_concrete":336,"farmersdelight:hamburger":3},"minecraft:mined":{"minecraft:dark_oak_planks":20,"minecraft:jungle_slab":1,"minecraft:crafting_table":3,"minecraft:jungle_stairs":2,"minecraft:grass_block":42,"minecraft:jungle_planks":4,"minecraft:chest":1,"minecraft:tall_grass":6,"minecraft:cobblestone":2,"minecraft:oak_planks":17,"minecraft:sandstone":20,"minecraft:dark_oak_slab":1,"minecraft:iron_ore":2,"farmersdelight:cutting_board":1,"minecraft:gray_bed":3,"minecraft:pumpkin":10,"minecraft:dark_oak_stairs":6,"minecraft:grass":144,"minecraft:coal_ore":9,"minecraft:oak_log":29,"minecraft:sand":58,"minecraft:dirt":12,"minecraft:stone":34},"minecraft:killed_by":{"isleofberk:gronckle":1},"minecraft:crafted":{"minecraft:oak_planks":108,"minecraft:stone_shovel":1,"minecraft:crafting_table":1,"farmersdelight:iron_knife":1,"minecraft:stone_axe":2,"farmersdelight:beef_patty":4,"farmersdelight:cutting_board":1,"minecraft:stick":16,"minecraft:iron_ingot":1,"minecraft:stone_pickaxe":1,"minecraft:oak_stairs":12,"minecraft:chest":1,"farmersdelight:cooked_bacon":4},"minecraft:killed":{"minecraft:pig":3,"minecraft:creeper":1,"minecraft:skeleton":1,"minecraft:sheep":4,"minecraft:zombie":6,"minecraft:chicken":5,"minecraft:cow":1},"minecraft:dropped":{"farmersdelight:hamburger":5,"farmersdelight:iron_knife":1,"minecraft:stone_axe":1,"minecraft:diamond":1,"minecraft:dark_oak_slab":1,"minecraft:stone_shovel":2,"farmersdelight:cooked_bacon":2,"minecraft:oak_planks":41,"minecraft:dirt":128,"minecraft:filled_map":1,"minecraft:jungle_slab":1,"minecraft:potion":1,"minecraft:spruce_log":320,"minecraft:stone_pickaxe":2,"minecraft:iron_pickaxe":1,"minecraft:dark_oak_planks":64},"minecraft:picked_up":{"minecraft:crafting_table":3,"minecraft:feather":6,"minecraft:chicken":5,"minecraft:leather":2,"minecraft:potion":1,"minecraft:filled_map":1,"farmersdelight:bacon":6,"minecraft:tuff":1,"minecraft:oak_log":27,"farmersdelight:cutting_board":1,"minecraft:dirt":55,"minecraft:paper":3,"minecraft:raw_copper":5,"farmersdelight:mutton_chops":2,"farmersdelight:iron_knife":1,"minecraft:wheat_seeds":6,"minecraft:cobbled_deepslate":6,"minecraft:beef":3,"minecraft:gray_bed":4,"minecraft:oak_planks":57,"minecraft:dark_oak_stairs":5,"minecraft:egg":2,"minecraft:raw_iron":1,"minecraft:sandstone":20,"minecraft:dark_oak_slab":1,"minecraft:pumpkin":8,"farmersdelight:minced_beef":4,"minecraft:porkchop":9,"minecraft:sand":53,"minecraft:jungle_planks":4,"farmersdelight:chicken_cuts":4,"minecraft:jungle_slab":1,"minecraft:dark_oak_planks":19,"minecraft:arrow":1,"minecraft:stone_shovel":1,"minecraft:rotten_flesh":4,"minecraft:stone_axe":2,"minecraft:jungle_stairs":2,"minecraft:bone_meal":2,"minecraft:bread":1,"minecraft:mutton":5,"minecraft:coal":9,"minecraft:white_wool":4,"minecraft:cobblestone":135},"minecraft:custom":{"minecraft:interact_with_furnace":8,"minecraft:mob_kills":22,"minecraft:interact_with_crafting_table":10,"minecraft:bell_ring":1,"minecraft:time_since_death":161402,"minecraft:sleep_in_bed":12,"minecraft:time_since_rest":16267,"minecraft:sprint_one_cm":206004,"minecraft:damage_taken":534,"minecraft:walk_one_cm":193279,"minecraft:drop":28,"minecraft:damage_dealt":2542,"minecraft:swim_one_cm":14281,"minecraft:fly_one_cm":280428,"minecraft:open_chest":14,"minecraft:play_time":172395,"minecraft:deaths":2,"minecraft:sneak_time":58,"minecraft:walk_under_water_one_cm":3328,"minecraft:jump":985,"minecraft:walk_on_water_one_cm":3141,"minecraft:total_world_time":172395,"minecraft:fall_one_cm":21238},"minecraft:broken":{"minecraft:stone_axe":1}},"DataVersion":2975}